{
  "info": {
    "_postman_id": "8d659637-4fae-4bb9-96dd-c356690e46ea",
    "name": "AssetSphere Bootstrap",
    "schema": "https://schema.getpostman.com/json/collection/v2.1.0/collection.json",
    "description": "Module 1 bootstrap validation collection."
  },
  "item": [
    {
      "name": "Health Check",
      "request": {
        "method": "GET",
        "header": [],
        "url": {
          "raw": "{{baseUrl}}/api/v1/health",
          "host": [
            "{{baseUrl}}"
          ],
          "path": [
            "api",
            "v1",
            "health"
          ]
        }
      },
      "response": []
    }
  ],
  "variable": [
    {
      "key": "baseUrl",
      "value": "http://localhost:4000"
    }
  ]
}
